Visualize_Logs/__init__.py
Visualize_Logs/__main__.py
Visualize_Logs/objects/__init__.py
Visualize_Logs/objects/CuckooJSONReport.py
Visualize_Logs/objects/Exceptions.py
Visualize_Logs/objects/ProcMonCSV.py
visualize_logs-20161112.2.dist-info/DESCRIPTION.rst
visualize_logs-20161112.2.dist-info/entry_points.txt
visualize_logs-20161112.2.dist-info/METADATA
visualize_logs-20161112.2.dist-info/metadata.json
visualize_logs-20161112.2.dist-info/RECORD
visualize_logs-20161112.2.dist-info/top_level.txt
visualize_logs-20161112.2.dist-info/WHEEL
