Metadata-Version: 2.0
Name: visualize-logs
Version: 20161112.2
Summary: A Python library and command line tools to provide log visualization.
Home-page: https://github.com/keithjjones/visualize_logs
Author: Keith J. Jones
Author-email: keith@keithjjones.com
License: CC BY-SA
Platform: UNKNOWN
Requires-Dist: networkx
Requires-Dist: pandas
Requires-Dist: plotly (>=1.9.0)
Requires-Dist: pydotplus
